WuaiPojieLuntanjinghuaJi2019DiliuBufen/README.md
WuaiPojieLuntanjinghuaJi2019DiliuBufen/__init__.py
WuaiPojieLuntanjinghuaJi2019DiliuBufen/__main__.py
WuaiPojieLuntanjinghuaJi2019DiliuBufen/file.epub
WuaiPojieLuntanjinghuaJi2019DiliuBufen/index.html
WuaiPojieLuntanjinghuaJi2019DiliuBufen/css/__init__.py
WuaiPojieLuntanjinghuaJi2019DiliuBufen/css/annotations.css
WuaiPojieLuntanjinghuaJi2019DiliuBufen/css/main.css
WuaiPojieLuntanjinghuaJi2019DiliuBufen/css/normalize.css
WuaiPojieLuntanjinghuaJi2019DiliuBufen/css/popup.css
WuaiPojieLuntanjinghuaJi2019DiliuBufen/font/__init__.py
WuaiPojieLuntanjinghuaJi2019DiliuBufen/font/fontello.eot
WuaiPojieLuntanjinghuaJi2019DiliuBufen/font/fontello.svg
WuaiPojieLuntanjinghuaJi2019DiliuBufen/font/fontello.ttf
WuaiPojieLuntanjinghuaJi2019DiliuBufen/font/fontello.woff
WuaiPojieLuntanjinghuaJi2019DiliuBufen/img/__init__.py
WuaiPojieLuntanjinghuaJi2019DiliuBufen/img/annotator-glyph-sprite.png
WuaiPojieLuntanjinghuaJi2019DiliuBufen/img/annotator-icon-sprite.png
WuaiPojieLuntanjinghuaJi2019DiliuBufen/img/apple-touch-icon.png
WuaiPojieLuntanjinghuaJi2019DiliuBufen/img/cancelfullscreen.png
WuaiPojieLuntanjinghuaJi2019DiliuBufen/img/close.png
WuaiPojieLuntanjinghuaJi2019DiliuBufen/img/fullscreen.png
WuaiPojieLuntanjinghuaJi2019DiliuBufen/img/loader.gif
WuaiPojieLuntanjinghuaJi2019DiliuBufen/img/menu-icon.png
WuaiPojieLuntanjinghuaJi2019DiliuBufen/img/save.png
WuaiPojieLuntanjinghuaJi2019DiliuBufen/img/saved.png
WuaiPojieLuntanjinghuaJi2019DiliuBufen/img/settings-s.png
WuaiPojieLuntanjinghuaJi2019DiliuBufen/img/settings.png
WuaiPojieLuntanjinghuaJi2019DiliuBufen/img/star.png
WuaiPojieLuntanjinghuaJi2019DiliuBufen/js/__init__.py
WuaiPojieLuntanjinghuaJi2019DiliuBufen/js/epub.js
WuaiPojieLuntanjinghuaJi2019DiliuBufen/js/epub.min.js
WuaiPojieLuntanjinghuaJi2019DiliuBufen/js/epub.min.map
WuaiPojieLuntanjinghuaJi2019DiliuBufen/js/hooks.min.js
WuaiPojieLuntanjinghuaJi2019DiliuBufen/js/hooks.min.map
wuai_pojie_luntanjinghua_ji_2019_diliu_bufen-2024.3.5.0.dist-info/METADATA
wuai_pojie_luntanjinghua_ji_2019_diliu_bufen-2024.3.5.0.dist-info/WHEEL
wuai_pojie_luntanjinghua_ji_2019_diliu_bufen-2024.3.5.0.dist-info/entry_points.txt
wuai_pojie_luntanjinghua_ji_2019_diliu_bufen-2024.3.5.0.dist-info/top_level.txt
wuai_pojie_luntanjinghua_ji_2019_diliu_bufen-2024.3.5.0.dist-info/RECORD
